src/eodFunc/finData.py
eodfunc-0.2.dist-info/METADATA
eodfunc-0.2.dist-info/WHEEL
eodfunc-0.2.dist-info/licenses/LICENSE
eodfunc-0.2.dist-info/RECORD
